[{"Info":"氣壓總壓檢知(7kg/cm3 up)","NodeID":"ns=4;s=APPL.system.di_AirPressNotEnough","BondingCableTerminal":"I00","KEBA_Definition":"DI_00","SensorType":1},{"Info":"預留","NodeID":null,"BondingCableTerminal":"I01","KEBA_Definition":"DI_01","SensorType":1},{"Info":"油壓單元液位檢知(低液位)","NodeID":"ns=4;s=APPL.OilMaintenance1.di_OilLevelOk","BondingCableTerminal":"I02","KEBA_Definition":"DI_02","SensorType":1},{"Info":"潤滑壓力檢知","NodeID":"ns=4;s=APPL.Lubrication1.di_LubPressureAchieved","BondingCableTerminal":"I03","KEBA_Definition":"DI_03","SensorType":1}]